beetsplug/VGMCollection.py
beetsplug/VGMplug.py
beetsplug/__init__.py
beets_vgmdb-1.3.4.dist-info/METADATA
beets_vgmdb-1.3.4.dist-info/WHEEL
beets_vgmdb-1.3.4.dist-info/top_level.txt
beets_vgmdb-1.3.4.dist-info/RECORD
