Metadata-Version: 2.4
Name: beets-vgmdb
Version: 1.3.4
Summary: Beets VGMdb metadata plugin and collection manager.
Author-email: HO ZhenWai Olivier <hozhenwai@gmail.com>
Project-URL: Source, https://github.com/HOZHENWAI/Beets-Plugin_VGMdb
Requires-Dist: requests
Requires-Dist: pathlib
Requires-Dist: beets>=2.4.0
Requires-Dist: beautifulsoup4
Requires-Dist: lxml
